__init__.py
telegraphist/__init__.py
telegraphist/game.py
telegraphist/input.py
telegraphist/levels.py
telegraphist/morse_code.py
telegraphist/sfx/dash.wav
telegraphist/sfx/dot.mp3
telegraphist/sfx/dot.wav
telegraphist/sfx/error.wav
telegraphist/sfx/level_up.wav
telegraphist/sfx/success.wav
the_telegraphist-1.0.8.dist-info/licenses/LICENSE
the_telegraphist-1.0.8.dist-info/METADATA
the_telegraphist-1.0.8.dist-info/WHEEL
the_telegraphist-1.0.8.dist-info/entry_points.txt
the_telegraphist-1.0.8.dist-info/top_level.txt
the_telegraphist-1.0.8.dist-info/RECORD
