Metadata-Version: 2.4
Name: the-telegraphist
Version: 1.0.8
Summary: A Python-based rhythm game about transmitting messages in Morse code.
Author-email: Chinmay Shet <chishxd@gmail.com>
License-Expression: MIT
Classifier: Programming Language :: Python :: 3
Classifier: Operating System :: OS Independent
Classifier: Topic :: Games/Entertainment
Requires-Python: >=3.13
License-File: LICENSE
Requires-Dist: pynput
Requires-Dist: rich
Requires-Dist: playsound3
Dynamic: license-file
